[
    {
        "_id": "642c155b2c4774f05c36eeaa",
        "name": "Haddock",
        "recipe": "Chargrilled fresh tuna steak (served medium rare) on classic Niçoise salad with French beans.",
        "image": "https://cdn.loveandlemons.com/wp-content/uploads/2021/04/green-salad-1-580x803.jpg",
        "category": "salad",
        "price": 14.7
    },
    {
        "_id": "642c155b2c4774f05c36eeb9",
        "name": "Haddock",
        "recipe": "Chargrilled fresh tuna steak (served medium rare) on classic Niçoise salad with French beans.",
        "image": "https://t4.ftcdn.net/jpg/07/04/98/39/360_F_704983944_1zZKWb6ZeD0A1Xih0m403ezMSIu36TCX.jpg",
        "category": "drinks",
        "price": 14.7
    },
    {
        "_id": "642c155b2c4774f05c36ee7c",
        "name": "Escalope de Veau",
        "recipe": "Roasted duck breast (served pink) with gratin potato and a griottine cherry sauce",
        "image": "https://i.postimg.cc/8kjq3L6q/chicken-savoy-cabbage-maple-bacon.jpg",
        "category": "popular",
        "price": 14.5
    },
    {
        "_id": "642c155b2c4774f05c36ee88",
        "name": "Escalope de Veau",
        "recipe": "Pan roasted haddock fillet wrapped in smoked French bacon with pea purée and tomato and chive vinaigrette",
        "image": "https://www.allrecipes.com/thmb/JBIZ6MfBnSYUEDTK0a2tXqQp-qo=/1500x0/filters:no_upscale():max_bytes(150000):strip_icc()/AR-22137-Strawberry-Angel-Food-Dessert-4x3-7d658d0858f141fb8637f6a6472c84ef.jpg",
        "category": "dessert",
        "price": 12.5
    },
    {
        "_id": "642c155b2c4774f05c36ee7a",
        "name": "Roast Duck Breast",
        "recipe": "Roasted duck breast (served pink) with gratin potato and a griottine cherry sauce",
        "image": "https://i.postimg.cc/8kjq3L6q/chicken-savoy-cabbage-maple-bacon.jpg",
        "category": "popular",
        "price": 14.5
    },
    {
        "_id": "642c155b2c4774f05c36ee8c",
        "name": "Escalope de Veau",
        "recipe": "Pan roasted haddock fillet wrapped in smoked French bacon with pea purée and tomato and chive vinaigrette",
        "image": "https://www.allrecipes.com/thmb/JBIZ6MfBnSYUEDTK0a2tXqQp-qo=/1500x0/filters:no_upscale():max_bytes(150000):strip_icc()/AR-22137-Strawberry-Angel-Food-Dessert-4x3-7d658d0858f141fb8637f6a6472c84ef.jpg",
        "category": "dessert",
        "price": 12.5
    },
    {
        "_id": "642c155b2c4774f05c36ee94",
        "name": "Escalope de Veau",
        "recipe": "Pan roasted haddock fillet wrapped in smoked French bacon with pea purée and tomato and chive vinaigrette",
        "image": "https://www.foodandwine.com/thmb/Wd4lBRZz3X_8qBr69UOu2m7I2iw=/1500x0/filters:no_upscale():max_bytes(150000):strip_icc()/classic-cheese-pizza-FT-RECIPE0422-31a2c938fc2546c9a07b7011658cfd05.jpg",
        "category": "pizza",
        "price": 12.5
    },
    {
        "_id": "642c155b2c4774f05c36ee9e",
        "name": "Breton Fish Stew",
        "recipe": "Chargrilled chicken with avocado, baby gem lettuce, baby spinach, shallots, French beans, walnuts, croutons and a mustard dressing",
        "image": "https://www.foodandwine.com/thmb/Wd4lBRZz3X_8qBr69UOu2m7I2iw=/1500x0/filters:no_upscale():max_bytes(150000):strip_icc()/classic-cheese-pizza-FT-RECIPE0422-31a2c938fc2546c9a07b7011658cfd05.jpg",
        "category": "pizza",
        "price": 12.9
    },
    {
        "_id": "642c155b2c4774f05c36eea6",
        "name": "Chicken and Walnut Salad",
        "recipe": "Pan roasted pork belly with gratin potato, braised Savoy cabbage, apples, thyme and calvados jus",
        "image": "https://cdn.loveandlemons.com/wp-content/uploads/2021/04/green-salad-1-580x803.jpg",
        "category": "salad",
        "price": 13.5
    },
    {
        "_id": "642c155b2c4774f05c36eeaf",
        "name": "Escalope de Veau",
        "recipe": "Pan roasted haddock fillet wrapped in smoked French bacon with pea purée and tomato and chive vinaigrette",
        "image": "https://i2.wp.com/www.downshiftology.com/wp-content/uploads/2023/09/Vegetable-Soup-main.jpg",
        "category": "soup",
        "price": 12.5
    },
    {
        "_id": "642c155b2c4774f05c36ee89",
        "name": "Chicken and Walnut Salad",
        "recipe": "Pan roasted pork belly with gratin potato, braised Savoy cabbage, apples, thyme and calvados jus",
        "image": "https://assets.bonappetit.com/photos/65bbc64efae81660e8192cc9/1:1/w_2560%2Cc_limit/20240130-WEB-0311.jpg",
        "category": "dessert",
        "price": 13.5
    },
    {
        "_id": "642c155b2c4774f05c36ee8a",
        "name": "Escalope de Veau",
        "recipe": "Pan roasted haddock fillet wrapped in smoked French bacon with pea purée and tomato and chive vinaigrette",
        "image": "https://www.southernliving.com/thmb/HFXfirNv58YxjV2uWi4Ima6rkD4=/1500x0/filters:no_upscale():max_bytes(150000):strip_icc()/2665601_ErinN_0213-2000-7b88f1a2e1bd40bba7070fc01476cf3d.jpg",
        "category": "dessert",
        "price": 12.5
    },
    {
        "_id": "642c155b2c4774f05c36ee96",
        "name": "Fish Parmentier",
        "recipe": "Sautéed breaded veal escalope with watercress, lemon and veal jus.",
        "image": "https://upload.wikimedia.org/wikipedia/commons/9/91/Pizza-3007395.jpg",
        "category": "pizza",
        "price": 9.5
    },
    {
        "_id": "642c155b2c4774f05c36ee81",
        "name": "Tuna Niçoise",
        "recipe": "Warm goats cheese and roasted vegetable salad with black olive tapenade crostini",
        "image": "https://cdn.tatlerasia.com/tatlerasia/i/2022/08/02082450-031a7847-2-hotel-icon_cover_1500x1001.png",
        "category": "offered",
        "price": 10.5
    },
    {
        "_id": "642c155b2c4774f05c36ee84",
        "name": "Roast Duck Breast",
        "recipe": "Roasted duck breast (served pink) with gratin potato and a griottine cherry sauce",
        "image": "https://1.bp.blogspot.com/-0XtE0a-MFqo/T2-avwAvlPI/AAAAAAAAC5I/Xl8tPCD02vc/s1600/Banana+caramel+cream+mini+dessert.jpg",
        "category": "dessert",
        "price": 14.5
    },
    {
        "_id": "642c155b2c4774f05c36eea4",
        "name": "Chicken and Walnut Salad",
        "recipe": "Pan roasted pork belly with gratin potato, braised Savoy cabbage, apples, thyme and calvados jus",
        "image": "https://www.twopeasandtheirpod.com/wp-content/uploads/2021/10/Easy-Spinach-Salad-8-1-500x500.jpg",
        "category": "salad",
        "price": 13.5
    },
    {
        "_id": "642c155b2c4774f05c36eea5",
        "name": "Fish Parmentier",
        "recipe": "Sautéed breaded veal escalope with watercress, lemon and veal jus.",
        "image": "https://www.twopeasandtheirpod.com/wp-content/uploads/2021/10/Easy-Spinach-Salad-8-1-500x500.jpg",
        "category": "salad",
        "price": 9.5
    },
    {
        "_id": "642c155b2c4774f05c36ee87",
        "name": "Chicken and Walnut Salad",
        "recipe": "Pan roasted pork belly with gratin potato, braised Savoy cabbage, apples, thyme and calvados jus",
        "image": "https://www.bhg.com/thmb/9PccF_menBy-F4VsJEsWFMqS19c=/1244x0/filters:no_upscale():strip_icc()/fresh-fruit-cream-tarts-R162003-1106f8279f804aa9bb72832aa0d8c135.jpg",
        "category": "dessert",
        "price": 13.5
    },
    {
        "_id": "642c155b2c4774f05c36ee83",
        "name": "Chicken and Walnut Salad",
        "recipe": "Pan roasted pork belly with gratin potato, braised Savoy cabbage, apples, thyme and calvados jus",
        "image": "https://cdn.tatlerasia.com/tatlerasia/i/2022/08/02082450-031a7847-2-hotel-icon_cover_1500x1001.png",
        "category": "offered",
        "price": 13.5
    },
    {
        "_id": "642c155b2c4774f05c36ee7f",
        "name": "Roasted duck breast",
        "recipe": "Roasted duck breast (served pink) with gratin potato and a griottine cherry sauce",
        "image": "https://i.postimg.cc/8kjq3L6q/chicken-savoy-cabbage-maple-bacon.jpg",
        "category": "popular",
        "price": 14.5
    },
    {
        "_id": "642c155b2c4774f05c36eea8",
        "name": "Chicken and Walnut Salad",
        "recipe": "Pan roasted pork belly with gratin potato, braised Savoy cabbage, apples, thyme and calvados jus",
        "image": "https://www.thespruceeats.com/thmb/2GoDt7juuaU7lxtQDq-_IjEr6t8=/1500x0/filters:no_upscale():max_bytes(150000):strip_icc()/SES-our-favorite-simple-green-salad-recipe-7370448-hero-01-4ca9788a0a3c4d53b70f1d07f8382b7f.jpg",
        "category": "salad",
        "price": 13.5
    },
    {
        "_id": "642c155b2c4774f05c36eeba",
        "name": "Haddock",
        "recipe": "Chargrilled fresh tuna steak (served medium rare) on classic Niçoise salad with French beans.",
        "image": "https://t4.ftcdn.net/jpg/05/56/12/01/360_F_556120108_w6ookKo38pgEvV812HBOq2tj2Y9aomQf.jpg",
        "category": "drinks",
        "price": 14.7
    },
    {
        "_id": "642c155b2c4774f05c36ee80",
        "name": "Roast Duck Breast",
        "recipe": "Roasted duck breast (served pink) with gratin potato and a griottine cherry sauce",
        "image": "https://cdn.tatlerasia.com/tatlerasia/i/2024/05/09120602-charred-cauliflower-back-alley-pasta-shairi-jay_cover_1280x854.jpeg",
        "category": "offered",
        "price": 14.5
    },
    {
        "_id": "642c155b2c4774f05c36ee90",
        "name": "Fish Parmentier",
        "recipe": "Sautéed breaded veal escalope with watercress, lemon and veal jus.",
        "image": "https://biancazapatka.com/wp-content/uploads/2020/07/tiramisu-dessert-easy-vegan.jpg",
        "category": "dessert",
        "price": 9.5
    },
    {
        "_id": "642c155b2c4774f05c36eeb0",
        "name": "Chicken and Walnut Salad",
        "recipe": "Pan roasted pork belly with gratin potato, braised Savoy cabbage, apples, thyme and calvados jus",
        "image": "https://i2.wp.com/www.downshiftology.com/wp-content/uploads/2023/09/Vegetable-Soup-main.jpg",
        "category": "soup",
        "price": 13.5
    },
    {
        "_id": "642c155b2c4774f05c36ee8d",
        "name": "Chicken and Walnut Salad",
        "recipe": "Pan roasted pork belly with gratin potato, braised Savoy cabbage, apples, thyme and calvados jus",
        "image": "https://funmoneymom.com/wp-content/uploads/2023/04/Oreo-Cheesecake-Balls-recipe-card-500x500.jpg",
        "category": "dessert",
        "price": 13.5
    },
    {
        "_id": "642c155b2c4774f05c36ee8e",
        "name": "Escalope de Veau",
        "recipe": "Pan roasted haddock fillet wrapped in smoked French bacon with pea purée and tomato and chive vinaigrette",
        "image": "https://www.bakingbeauty.net/wp-content/uploads/2016/04/oreo-buckeyes-3-e1460941018182.jpg",
        "category": "dessert",
        "price": 12.5
    },
    {
        "_id": "642c155b2c4774f05c36eea7",
        "name": "Fish Parmentier",
        "recipe": "Sautéed breaded veal escalope with watercress, lemon and veal jus.",
        "image": "https://www.thespruceeats.com/thmb/2GoDt7juuaU7lxtQDq-_IjEr6t8=/1500x0/filters:no_upscale():max_bytes(150000):strip_icc()/SES-our-favorite-simple-green-salad-recipe-7370448-hero-01-4ca9788a0a3c4d53b70f1d07f8382b7f.jpg",
        "category": "salad",
        "price": 9.5
    },
    {
        "_id": "642c155b2c4774f05c36ee99",
        "name": "Goats Cheese Pizza",
        "recipe": "Roasted duck breast (served pink) with gratin potato and a griottine cherry sauce",
        "image": "https://upload.wikimedia.org/wikipedia/commons/9/91/Pizza-3007395.jpg",
        "category": "pizza",
        "price": 14.5
    },
    {
        "_id": "642c155b2c4774f05c36eeb3",
        "name": "Fish Parmentier",
        "recipe": "Sautéed breaded veal escalope with watercress, lemon and veal jus.",
        "image": "https://i2.wp.com/www.downshiftology.com/wp-content/uploads/2023/09/Vegetable-Soup-main.jpg",
        "category": "soup",
        "price": 9.5
    },
    {
        "_id": "642c155b2c4774f05c36eeb5",
        "name": "Fish Parmentier",
        "recipe": "Sautéed breaded veal escalope with watercress, lemon and veal jus.",
        "image": "https://www.thespruceeats.com/thmb/lko3xX8clhOrC894t9Drb6MoiX0=/1500x0/filters:no_upscale():max_bytes(150000):strip_icc()/easy-and-hearty-vegetable-soup-99538-hero-01-1d3b936ff03144af95ddca7640259c11.jpg",
        "category": "soup",
        "price": 9.5
    },
    {
        "_id": "642c155b2c4774f05c36eeb6",
        "name": "Haddock",
        "recipe": "Chargrilled fresh tuna steak (served medium rare) on classic Niçoise salad with French beans.",
        "image": "https://www.thespruceeats.com/thmb/lko3xX8clhOrC894t9Drb6MoiX0=/1500x0/filters:no_upscale():max_bytes(150000):strip_icc()/easy-and-hearty-vegetable-soup-99538-hero-01-1d3b936ff03144af95ddca7640259c11.jpg",
        "category": "soup",
        "price": 14.7
    },
    {
        "_id": "642c155b2c4774f05c36eeb8",
        "name": "Haddock",
        "recipe": "Chargrilled fresh tuna steak (served medium rare) on classic Niçoise salad with French beans.",
        "image": "https://www.seriouseats.com/thmb/DvSDZoMw8WSOQFAMgf3L2wlfY9Y=/1500x0/filters:no_upscale():max_bytes(150000):strip_icc()/053123_TomatoSoup-MPPSoupsAndStews-Morgan-Hunt-Glaze-f59a081d7efb4625a75a1a907a6b1cbf.jpg",
        "category": "soup",
        "price": 14.7
    },
    {
        "_id": "642c155b2c4774f05c36ee7e",
        "name": "Fish Parmentier",
        "recipe": "Roasted duck breast (served pink) with gratin potato and a griottine cherry sauce",
        "image": "https://img.hellofresh.com/f_auto,fl_lossy,q_auto,w_1200/hellofresh_s3/image/seared-duck-breast-728a8c10-f3b0ba7b.jpg",
        "category": "popular",
        "price": 14.5
    },
    {
        "_id": "642c155b2c4774f05c36ee8b",
        "name": "Chicken and Walnut Salad",
        "recipe": "Pan roasted pork belly with gratin potato, braised Savoy cabbage, apples, thyme and calvados jus",
        "image": "https://confessionsofabakingqueen.com/wp-content/uploads/2012/10/oreo-truffle-balls-featured-image-1-of-1.jpg",
        "category": "dessert",
        "price": 13.5
    },
    {
        "_id": "642c155b2c4774f05c36ee8f",
        "name": "Chicken and Walnut Salad",
        "recipe": "Pan roasted pork belly with gratin potato, braised Savoy cabbage, apples, thyme and calvados jus",
        "image": "https://i.pinimg.com/originals/40/a6/b4/40a6b46f1cfac7477e26740059c84242.jpg",
        "category": "dessert",
        "price": 13.5
    },
    {
        "_id": "642c155b2c4774f05c36ee91",
        "name": "Haddock",
        "recipe": "Chargrilled fresh tuna steak (served medium rare) on classic Niçoise salad with French beans",
        "image": "https://thebakermama.com/wp-content/uploads/2013/07/IMG_7198-scaled.jpg",
        "category": "dessert",
        "price": 14.7
    },
    {
        "_id": "642c155b2c4774f05c36ee97",
        "name": "Haddock",
        "recipe": "Chargrilled fresh tuna steak (served medium rare) on classic Niçoise salad with French beans.",
        "image": "https://www.southernliving.com/thmb/3x3cJaiOvQ8-3YxtMQX0vvh1hQw=/1500x0/filters:no_upscale():max_bytes(150000):strip_icc()/2652401_QFSSL_SupremePizza_00072-d910a935ba7d448e8c7545a963ed7101.jpg",
        "category": "pizza",
        "price": 14.7
    },
    {
        "_id": "642c155b2c4774f05c36eea0",
        "name": "Roasted Pork Belly",
        "recipe": "Chargrilled chicken with avocado, baby gem lettuce, baby spinach, shallots, French beans, walnuts, croutons and a mustard dressing",
        "image": "https://www.southernliving.com/thmb/3x3cJaiOvQ8-3YxtMQX0vvh1hQw=/1500x0/filters:no_upscale():max_bytes(150000):strip_icc()/2652401_QFSSL_SupremePizza_00072-d910a935ba7d448e8c7545a963ed7101.jpg",
        "category": "pizza",
        "price": 14.5
    },
    {
        "_id": "642c155b2c4774f05c36eea9",
        "name": "Fish Parmentier",
        "recipe": "Sautéed breaded veal escalope with watercress, lemon and veal jus.",
        "image": "https://thewoodenskillet.com/wp-content/uploads/2020/07/grilled-chicken-salad-recipe-1-1.jpg",
        "category": "salad",
        "price": 9.5
    },
    {
        "_id": "642c155b2c4774f05c36ee85",
        "name": "Tuna Niçoise",
        "recipe": "Warm goats cheese and roasted vegetable salad with black olive tapenade crostini",
        "image": "https://cdn.apartmenttherapy.info/image/upload/f_auto,q_auto:eco,c_fill,g_auto,w_1500,ar_3:2/k%2Frecipes%2F2023%2F2023-12-chocolate-delight%2Fchocolate-delight-recipe-1",
        "category": "dessert",
        "price": 10.5
    },
    {
        "_id": "642c155b2c4774f05c36ee93",
        "name": "Tuna Niçoise",
        "recipe": "Warm goats cheese and roasted vegetable salad with black olive tapenade crostini",
        "image": "https://www.simplyrecipes.com/thmb/KE6iMblr3R2Db6oE8HdyVsFSj2A=/1500x0/filters:no_upscale():max_bytes(150000):strip_icc()/__opt__aboutcom__coeus__resources__content_migration__simply_recipes__uploads__2019__09__easy-pepperoni-pizza-lead-3-1024x682-583b275444104ef189d693a64df625da.jpg",
        "category": "pizza",
        "price": 10.5
    },
    {
        "_id": "642c155b2c4774f05c36ee95",
        "name": "Chicken and Walnut Salad",
        "recipe": "Pan roasted pork belly with gratin potato, braised Savoy cabbage, apples, thyme and calvados jus",
        "image": "https://www.simplyrecipes.com/thmb/KE6iMblr3R2Db6oE8HdyVsFSj2A=/1500x0/filters:no_upscale():max_bytes(150000):strip_icc()/__opt__aboutcom__coeus__resources__content_migration__simply_recipes__uploads__2019__09__easy-pepperoni-pizza-lead-3-1024x682-583b275444104ef189d693a64df625da.jpg",
        "category": "pizza",
        "price": 13.5
    },
    {
        "_id": "642c155b2c4774f05c36ee9b",
        "name": "Goats Cheese Pizza",
        "recipe": "Roasted duck breast (served pink) with gratin potato and a griottine cherry sauce",
        "image": "https://theinspirespy.com/wp-content/uploads/2024/03/download.jpg",
        "category": "pizza",
        "price": 14.5
    },
    {
        "_id": "642c155b2c4774f05c36eeb7",
        "name": "Fish Parmentier",
        "recipe": "Sautéed breaded veal escalope with watercress, lemon and veal jus.",
        "image": "https://www.seriouseats.com/thmb/DvSDZoMw8WSOQFAMgf3L2wlfY9Y=/1500x0/filters:no_upscale():max_bytes(150000):strip_icc()/053123_TomatoSoup-MPPSoupsAndStews-Morgan-Hunt-Glaze-f59a081d7efb4625a75a1a907a6b1cbf.jpg",
        "category": "soup",
        "price": 9.5
    },
    {
        "_id": "642c155b2c4774f05c36ee9c",
        "name": "Breton Fish Stew",
        "recipe": "Chargrilled chicken with avocado, baby gem lettuce, baby spinach, shallots, French beans, walnuts, croutons and a mustard dressing",
        "image": "https://theinspirespy.com/wp-content/uploads/2024/03/download.jpg",
        "category": "pizza",
        "price": 12.9
    },
    {
        "_id": "642c155b2c4774f05c36ee9d",
        "name": "Goats Cheese Pizza",
        "recipe": "Roasted duck breast (served pink) with gratin potato and a griottine cherry sauce",
        "image": "https://www.simplyrecipes.com/thmb/KRw_r32s4gQeOX-d07NWY1OlOFk=/1500x0/filters:no_upscale():max_bytes(150000):strip_icc()/Simply-Recipes-Homemade-Pizza-Dough-Lead-Shot-1c-c2b1885d27d4481c9cfe6f6286a64342.jpg",
        "category": "pizza",
        "price": 14.5
    },
    {
        "_id": "642c155b2c4774f05c36eeac",
        "name": "Roasted Pork Belly",
        "recipe": "Chargrilled chicken with avocado, baby gem lettuce, baby spinach, shallots, French beans, walnuts, croutons and a mustard dressing",
        "image": "https://thewoodenskillet.com/wp-content/uploads/2020/07/grilled-chicken-salad-recipe-1-1.jpg",
        "category": "salad",
        "price": 14.5
    },
    {
        "_id": "642c155b2c4774f05c36eeb4",
        "name": "Haddock",
        "recipe": "Chargrilled fresh tuna steak (served medium rare) on classic Niçoise salad with French beans.",
        "image": "https://www.allrecipes.com/thmb/PKh_MtthZMtG1flNmud0MNgRK7w=/1500x0/filters:no_upscale():max_bytes(150000):strip_icc()/13096-Cream-of-Mushroom-Soup-ddmfs-4x3-293-b505e37374d74e81807e8a93bcdd7bab.jpg",
        "category": "soup",
        "price": 14.7
    },
    {
        "_id": "642c155b2c4774f05c36ee98",
        "name": "Breton Fish Stew",
        "recipe": "Chargrilled chicken with avocado, baby gem lettuce, baby spinach, shallots, French beans, walnuts, croutons and a mustard dressing",
        "image": "https://topsecretrecipes.com/foodhackerblog/wp-content/uploads/2019/09/giordanos-famous-deep-dish-pizza-copycat-recipe-700.jpg",
        "category": "pizza",
        "price": 12.9
    },
    {
        "_id": "642c155b2c4774f05c36ee82",
        "name": "Escalope de Veau",
        "recipe": "Pan roasted haddock fillet wrapped in smoked French bacon with pea purée and tomato and chive vinaigrette",
        "image": "https://cdn.tatlerasia.com/tatlerasia/i/2024/05/09120602-charred-cauliflower-back-alley-pasta-shairi-jay_cover_1280x854.jpeg",
        "category": "offered",
        "price": 12.5
    },
    {
        "_id": "642c155b2c4774f05c36ee86",
        "name": "Escalope de Veau",
        "recipe": "Pan roasted haddock fillet wrapped in smoked French bacon with pea purée and tomato and chive vinaigrette",
        "image": "https://www.southernliving.com/thmb/z706skTv8rLcnFwyTEnMzr_H5zQ=/1500x0/filters:no_upscale():max_bytes(150000):strip_icc()/Southern-Living_27364_SR_Lemon-Lush_13190-fd96c709fc2946a7aeb5c869f9ad470e.jpg",
        "category": "dessert",
        "price": 12.5
    },
    {
        "_id": "642c155b2c4774f05c36ee9a",
        "name": "Breton Fish Stew",
        "recipe": "Chargrilled chicken with avocado, baby gem lettuce, baby spinach, shallots, French beans, walnuts, croutons and a mustard dressing",
        "image": "https://topsecretrecipes.com/foodhackerblog/wp-content/uploads/2019/09/giordanos-famous-deep-dish-pizza-copycat-recipe-700.jpg",
        "category": "pizza",
        "price": 12.9
    },
    {
        "_id": "642c155b2c4774f05c36eeab",
        "name": "Goats Cheese Pizza",
        "recipe": "Roasted duck breast (served pink) with gratin potato and a griottine cherry sauce",
        "image": "https://thewoodenskillet.com/wp-content/uploads/2020/07/grilled-chicken-salad-recipe-1-1.jpg",
        "category": "salad",
        "price": 14.5
    },
    {
        "_id": "642c155b2c4774f05c36eeb1",
        "name": "Fish Parmentier",
        "recipe": "Sautéed breaded veal escalope with watercress, lemon and veal jus.",
        "image": "https://www.allrecipes.com/thmb/PKh_MtthZMtG1flNmud0MNgRK7w=/1500x0/filters:no_upscale():max_bytes(150000):strip_icc()/13096-Cream-of-Mushroom-Soup-ddmfs-4x3-293-b505e37374d74e81807e8a93bcdd7bab.jpg",
        "category": "soup",
        "price": 9.5
    },
    {
        "_id": "642c155b2c4774f05c36eead",
        "name": "Roast Duck Breast",
        "recipe": "Roasted duck breast (served pink) with gratin potato and a griottine cherry sauce",
        "image": "https://www.allrecipes.com/thmb/PKh_MtthZMtG1flNmud0MNgRK7w=/1500x0/filters:no_upscale():max_bytes(150000):strip_icc()/13096-Cream-of-Mushroom-Soup-ddmfs-4x3-293-b505e37374d74e81807e8a93bcdd7bab.jpg",
        "category": "soup",
        "price": 14.5
    },
    {
        "_id": "642c155b2c4774f05c36eeae",
        "name": "Tuna Niçoise",
        "recipe": "Warm goats cheese and roasted vegetable salad with black olive tapenade crostini",
        "image": "https://www.allrecipes.com/thmb/PKh_MtthZMtG1flNmud0MNgRK7w=/1500x0/filters:no_upscale():max_bytes(150000):strip_icc()/13096-Cream-of-Mushroom-Soup-ddmfs-4x3-293-b505e37374d74e81807e8a93bcdd7bab.jpg",
        "category": "soup",
        "price": 10.5
    }
]